{
    "numcircuit": 3,
    "nameAlgorithm": "ghz",
    "averageQubits": 3.0,
    "nameSchedule": "MILQ_extend",
    "typeMachine": {
        "fake_belem": 5,
        "fake_manila": 5
    },
    "average_turnaroundTime": 14.333333333333334,
    "average_responseTime": 2.3333333333333335,
    "average_fidelity": 0.8697970679700506,
    "sampling_overhead": 0.0,
    "average_throughput": 0.13043478260869565,
    "average_utilization": 0.6,
    "time_generation": 3.5905826091766357,
    "makespan": 23.0
}