{
    "numcircuit": 14,
    "nameAlgorithm": "ghz",
    "averageQubits": 5.0,
    "nameSchedule": "FFD",
    "typeMachine": {
        "fake_belem": 5,
        "fake_manila": 5
    },
    "average_turnaroundTime": 55748.57142857143,
    "average_responseTime": 41686.857142857145,
    "average_fidelity": 0.7891297433485449,
    "sampling_overhead": 0.0,
    "average_throughput": 10589.714285714286,
    "average_utilization": 1.0,
    "scheduler_latency": 0.0067138671875,
    "makespan": 148256.0
}